CISPay/CISPay.py
CISPay/__init__.py
cispay-1.0.2.dist-info/METADATA
cispay-1.0.2.dist-info/WHEEL
cispay-1.0.2.dist-info/licenses/LICENSE
cispay-1.0.2.dist-info/RECORD
