Metadata-Version: 2.4
Name: CISPay
Version: 1.0.2
Summary: Library for Python 3+ to accept payments on CISPay
Project-URL: Homepage, https://github.com/CISPay/PythonLib
Author-email: dotmix <me@dotmix.eu>
License: MIT License
License-File: LICENSE
Keywords: api,payments
Classifier: License :: OSI Approved :: MIT License
Classifier: Programming Language :: Python
Classifier: Programming Language :: Python :: 3
Requires-Python: >=3.7
Requires-Dist: requests
